vspackrgb/__init__.py
vspackrgb/cython.cpython-313-aarch64-linux-gnu.so
vspackrgb/cython.pyi
vspackrgb/helpers.py
vspackrgb/numpy.py
vspackrgb/py.typed
vspackrgb/python.py
vspackrgb-1.0.0.dist-info/METADATA
vspackrgb-1.0.0.dist-info/WHEEL
vspackrgb-1.0.0.dist-info/RECORD
vspackrgb-1.0.0.dist-info/licenses/LICENSE
