Metadata-Version: 2.4
Name: vspackrgb
Version: 1.0.0
Summary: RGB packing for VapourSynth frames
Project-URL: Source Code, https://github.com/Jaded-Encoding-Thaumaturgy/vs-view/tree/main/src/vspackrgb
Project-URL: Bug Tracker, https://github.com/Jaded-Encoding-Thaumaturgy/vs-view/issues
Project-URL: Contact, https://discord.gg/XTpc6Fa9eB
License: MIT License
License-File: LICENSE
Keywords: aarch64,arm,arm64,cython,packing,rgb,vapoursynth
Classifier: License :: OSI Approved :: MIT License
Classifier: Operating System :: MacOS :: MacOS X
Classifier: Operating System :: Microsoft :: Windows
Classifier: Operating System :: POSIX :: Linux
Classifier: Programming Language :: Python :: 3
Classifier: Programming Language :: Python :: 3.12
Classifier: Programming Language :: Python :: 3.13
Classifier: Programming Language :: Python :: 3.14
Classifier: Typing :: Typed
Requires-Python: >=3.12
Requires-Dist: vapoursynth
Provides-Extra: numpy
Requires-Dist: numpy>=2.0.0; extra == 'numpy'
